cs/edit.py
cs.edit-20220429.dist-info/METADATA
cs.edit-20220429.dist-info/WHEEL
cs.edit-20220429.dist-info/top_level.txt
cs.edit-20220429.dist-info/RECORD
